{"trial_id": "0482", "hyperparameters": {"space": [{"class_name": "Choice", "config": {"name": "activation", "default": "relu", "conditions": [], "values": ["relu", "tanh", "sigmoid", "elu", "selu", "softmax"], "ordered": false}}, {"class_name": "Int", "config": {"name": "first_units", "default": null, "conditions": [], "min_value": 1, "max_value": 10, "step": 2, "sampling": "linear"}}, {"class_name": "Int", "config": {"name": "num_layers", "default": null, "conditions": [], "min_value": 1, "max_value": 6, "step": 1, "sampling": "linear"}}, {"class_name": "Int", "config": {"name": "units_0", "default": null, "conditions": [], "min_value": 1, "max_value": 10, "step": 2, "sampling": "linear"}}, {"class_name": "Int", "config": {"name": "units_1", "default": null, "conditions": [], "min_value": 1, "max_value": 10, "step": 2, "sampling": "linear"}}, {"class_name": "Int", "config": {"name": "units_2", "default": null, "conditions": [], "min_value": 1, "max_value": 10, "step": 2, "sampling": "linear"}}, {"class_name": "Int", "config": {"name": "units_3", "default": null, "conditions": [], "min_value": 1, "max_value": 10, "step": 2, "sampling": "linear"}}, {"class_name": "Int", "config": {"name": "units_4", "default": null, "conditions": [], "min_value": 1, "max_value": 10, "step": 2, "sampling": "linear"}}, {"class_name": "Int", "config": {"name": "units_5", "default": null, "conditions": [], "min_value": 1, "max_value": 10, "step": 2, "sampling": "linear"}}], "values": {"activation": "elu", "first_units": 7, "num_layers": 6, "units_0": 1, "units_1": 7, "units_2": 3, "units_3": 5, "units_4": 7, "units_5": 7, "tuner/epochs": 34, "tuner/initial_epoch": 0, "tuner/bracket": 1, "tuner/round": 0}}, "metrics": {"metrics": {"accuracy": {"direction": "max", "observations": [{"value": [0.6394461989402771], "step": 7}]}, "loss": {"direction": "min", "observations": [{"value": [-0.19590309262275696], "step": 7}]}, "val_accuracy": {"direction": "max", "observations": [{"value": [0.6734463572502136], "step": 7}]}, "val_loss": {"direction": "min", "observations": [{"value": [-0.056107766926288605], "step": 7}]}}}, "score": 0.6734463572502136, "best_step": 7, "status": "COMPLETED", "message": null}